online_store/__init__.py
online_store/__main__.py
online_store/order_management/__init__.py
online_store/order_management/__main__.py
online_store/user_management/__init__.py
online_store/user_management/__main__.py
hw6_cu_zimin-0.1.0.dist-info/METADATA
hw6_cu_zimin-0.1.0.dist-info/WHEEL
hw6_cu_zimin-0.1.0.dist-info/top_level.txt
hw6_cu_zimin-0.1.0.dist-info/RECORD
